plcrex/__init__.py
plcrex/__main__.py
plcrex/cli.py
plcrex/data/__init__.py
plcrex/data/grammars/DOTgrammar.lark
plcrex/data/grammars/FBD_QRZgrammar.lark
plcrex/data/grammars/FBD_SCTXgrammar.lark
plcrex/data/grammars/FBD_STgrammar.lark
plcrex/data/grammars/SCChart_grammar.lark
plcrex/data/grammars/SMTgrammar.lark
plcrex/data/grammars/SMVgrammar.lark
plcrex/data/grammars/SMVgrammar_v2.lark
plcrex/data/grammars/SPECgrammar.lark
plcrex/data/grammars/STgrammar.lark
plcrex/data/grammars/STgrammar_Beckhoff.lark
plcrex/data/grammars/__init__.py
plcrex/data/grammars/qrz_grammar.lark
plcrex/data/grammars/qrz_grammar_EOL.lark
plcrex/data/grammars/scl_grammar.lark
plcrex/data/grammars/scl_grammar_EOL.lark
plcrex/data/grammars/st_grammar.lark
plcrex/data/grammars/st_grammar_EOL.lark
plcrex/data/tc6/__init__.py
plcrex/data/tc6/tc6_xml_v10.xsd
plcrex/data/tc6/tc6_xml_v201.xsd
plcrex/models/__init__.py
plcrex/models/fbd/__init__.py
plcrex/models/pim/__init__.py
plcrex/models/qrz/__init__.py
plcrex/models/qrz/qrz_model.cp39-win_amd64.pyd
plcrex/models/scl/__init__.py
plcrex/models/scl/scl_model.cp39-win_amd64.pyd
plcrex/models/smt/__init__.py
plcrex/models/smt/z3py/__init__.py
plcrex/models/smv/__init__.py
plcrex/models/smv/nusmv/__init__.py
plcrex/models/smv/nusmvi/__init__.py
plcrex/models/st/__init__.py
plcrex/models/st/st_model.cp39-win_amd64.pyd
plcrex/tools/__init__.py
plcrex/tools/fbd2st/__init__.py
plcrex/tools/fbd2st/call_fbd2st_compiler.py
plcrex/tools/fbd2st/pyd/fbd2st_compiler.cp39-win_amd64.pyd
plcrex/tools/fbd2x/__init__.py
plcrex/tools/fbd2x/call_fbd_optimizer.py
plcrex/tools/fbd2x/pyd/fbd_optimizer.cp39-win_amd64.pyd
plcrex/tools/fbdia/__init__.py
plcrex/tools/fbdia/call_io_analysis.py
plcrex/tools/fbdia/pyd/io_analysis.cp39-win_amd64.pyd
plcrex/tools/ieccheck/__init__.py
plcrex/tools/ieccheck/call_iec_checker.py
plcrex/tools/ieccheck/iec_checker.py
plcrex/tools/misc/__init__.py
plcrex/tools/misc/generic_functions.py
plcrex/tools/st2qrz/__init__.py
plcrex-2.0.0.dist-info/LICENSE
plcrex-2.0.0.dist-info/METADATA
plcrex-2.0.0.dist-info/WHEEL
plcrex-2.0.0.dist-info/top_level.txt
plcrex-2.0.0.dist-info/RECORD
