Metadata-Version: 2.1
Name: plcrex
Version: 2.0.0
Summary: PLCreX - Simplification, Transformation, Analysis, and Validation of IEC 61131-3 Programmable Logic Controllers
Author-email: "Marcel C. Werner" <plcrex.info@gmail.com>
License: GNU GENERAL PUBLIC LICENSE
Project-URL: Homepage, https://github.com/marwern/PLCreX
Project-URL: Bug Tracker, https://github.com/marwern/PLCreX/issues
Keywords: PLC,SPS,IEC-61131,FBD,ST,testing,development,verification
Classifier: Programming Language :: Python :: 3.9
Classifier: Operating System :: Microsoft :: Windows
Requires-Python: >=3.9
License-File: LICENSE
Requires-Dist: attrs ==23.1.0
Requires-Dist: click ==8.1.6
Requires-Dist: colorama ==0.4.5
Requires-Dist: coverage ==6.5.0
Requires-Dist: coverage-badge ==1.1.0
Requires-Dist: dd ==0.5.7
Requires-Dist: dicttoxml2 ==2.1.0
Requires-Dist: elementpath ==3.0.2
Requires-Dist: exceptiongroup ==1.2.0
Requires-Dist: iniconfig ==2.0.0
Requires-Dist: lark ==1.1.7
Requires-Dist: markdown-it-py ==3.0.0
Requires-Dist: mdurl ==0.1.2
Requires-Dist: packaging ==23.2
Requires-Dist: pluggy ==1.3.0
Requires-Dist: pydot ==1.4.2
Requires-Dist: pyeda ==0.29.0
Requires-Dist: Pygments ==2.17.2
Requires-Dist: pyparsing ==3.1.1
Requires-Dist: pytest ==7.2.0
Requires-Dist: rich ==13.5.1
Requires-Dist: termcolor ==2.3.0
Requires-Dist: tomli ==2.0.1
Requires-Dist: typer ==0.9.0
Requires-Dist: typing-extensions ==4.8.0
Requires-Dist: xmlschema ==2.1.1
Requires-Dist: z3-solver ==4.12.2.0
